{
  "annotations": {
    "list": [
      {
        "builtIn": 1,
        "datasource": { "type": "grafana", "uid": "-- Grafana --" },
        "enable": true,
        "hide": true,
        "iconColor": "rgba(0, 211, 255, 1)",
        "name": "Annotations & Alerts",
        "type": "dashboard"
      }
    ]
  },
  "description": "API Performance Dashboard - Application-level metrics (Istio Ambient compatible)",
  "editable": true,
  "fiscalYearStartMonth": 0,
  "graphTooltip": 1,
  "id": null,
  "links": [],
  "panels": [
    {
      "collapsed": false,
      "gridPos": { "h": 1, "w": 24, "x": 0, "y": 0 },
      "id": 100,
      "panels": [],
      "title": "API Overview (All Services)",
      "type": "row"
    },
    {
      "datasource": { "type": "prometheus", "uid": "${datasource}" },
      "fieldConfig": {
        "defaults": {
          "color": { "mode": "palette-classic" },
          "mappings": [],
          "thresholds": { "mode": "absolute", "steps": [{ "color": "green", "value": null }] },
          "unit": "reqps"
        },
        "overrides": []
      },
      "gridPos": { "h": 4, "w": 6, "x": 0, "y": 1 },
      "id": 1,
      "options": {
        "colorMode": "background",
        "graphMode": "area",
        "justifyMode": "auto",
        "orientation": "auto",
        "reduceOptions": { "calcs": ["lastNotNull"], "fields": "", "values": false },
        "textMode": "auto"
      },
      "pluginVersion": "10.2.0",
      "targets": [
        {
          "datasource": { "type": "prometheus", "uid": "${datasource}" },
          "expr": "sum(rate({__name__=~\".*_service_http_requests_total\", namespace=~\"$namespace\"}[5m])) + sum(rate(http_server_requests_seconds_count{namespace=~\"$namespace\"}[5m])) or sum(rate({__name__=~\".*_service_http_requests_total\", namespace=~\"$namespace\"}[5m]))",
          "legendFormat": "Total RPS",
          "refId": "A"
        }
      ],
      "title": "Total Request Rate",
      "type": "stat"
    },
    {
      "datasource": { "type": "prometheus", "uid": "${datasource}" },
      "fieldConfig": {
        "defaults": {
          "color": { "mode": "thresholds" },
          "decimals": 2,
          "mappings": [],
          "thresholds": {
            "mode": "absolute",
            "steps": [
              { "color": "green", "value": null },
              { "color": "yellow", "value": 1 },
              { "color": "red", "value": 5 }
            ]
          },
          "unit": "percent"
        },
        "overrides": []
      },
      "gridPos": { "h": 4, "w": 6, "x": 6, "y": 1 },
      "id": 2,
      "options": {
        "colorMode": "background",
        "graphMode": "area",
        "justifyMode": "auto",
        "orientation": "auto",
        "reduceOptions": { "calcs": ["lastNotNull"], "fields": "", "values": false },
        "textMode": "auto"
      },
      "pluginVersion": "10.2.0",
      "targets": [
        {
          "datasource": { "type": "prometheus", "uid": "${datasource}" },
          "expr": "100 * (sum(rate({__name__=~\".*_service_http_requests_total\", namespace=~\"$namespace\", status=\"5xx\"}[5m])) + sum(rate(http_server_requests_seconds_count{namespace=~\"$namespace\", status=~\"5.*\"}[5m])) or vector(0)) / (sum(rate({__name__=~\".*_service_http_requests_total\", namespace=~\"$namespace\"}[5m])) + sum(rate(http_server_requests_seconds_count{namespace=~\"$namespace\"}[5m])) or vector(1))",
          "legendFormat": "",
          "refId": "A"
        }
      ],
      "title": "Error Rate (5xx)",
      "type": "stat"
    },
    {
      "datasource": { "type": "prometheus", "uid": "${datasource}" },
      "fieldConfig": {
        "defaults": {
          "color": { "mode": "thresholds" },
          "mappings": [],
          "thresholds": {
            "mode": "absolute",
            "steps": [
              { "color": "green", "value": null },
              { "color": "yellow", "value": 200 },
              { "color": "red", "value": 500 }
            ]
          },
          "unit": "ms"
        },
        "overrides": []
      },
      "gridPos": { "h": 4, "w": 6, "x": 12, "y": 1 },
      "id": 3,
      "options": {
        "colorMode": "background",
        "graphMode": "area",
        "justifyMode": "auto",
        "orientation": "auto",
        "reduceOptions": { "calcs": ["lastNotNull"], "fields": "", "values": false },
        "textMode": "auto"
      },
      "pluginVersion": "10.2.0",
      "targets": [
        {
          "datasource": { "type": "prometheus", "uid": "${datasource}" },
          "expr": "histogram_quantile(0.50, sum(rate({__name__=~\".*_service_http_request_duration_seconds_bucket\", namespace=~\"$namespace\"}[5m])) by (le)) * 1000",
          "legendFormat": "",
          "refId": "A"
        }
      ],
      "title": "Latency p50",
      "type": "stat"
    },
    {
      "datasource": { "type": "prometheus", "uid": "${datasource}" },
      "fieldConfig": {
        "defaults": {
          "color": { "mode": "thresholds" },
          "mappings": [],
          "thresholds": {
            "mode": "absolute",
            "steps": [
              { "color": "green", "value": null },
              { "color": "yellow", "value": 300 },
              { "color": "red", "value": 500 }
            ]
          },
          "unit": "ms"
        },
        "overrides": []
      },
      "gridPos": { "h": 4, "w": 6, "x": 18, "y": 1 },
      "id": 4,
      "options": {
        "colorMode": "background",
        "graphMode": "area",
        "justifyMode": "auto",
        "orientation": "auto",
        "reduceOptions": { "calcs": ["lastNotNull"], "fields": "", "values": false },
        "textMode": "auto"
      },
      "pluginVersion": "10.2.0",
      "targets": [
        {
          "datasource": { "type": "prometheus", "uid": "${datasource}" },
          "expr": "histogram_quantile(0.95, sum(rate({__name__=~\".*_service_http_request_duration_seconds_bucket\", namespace=~\"$namespace\"}[5m])) by (le)) * 1000",
          "legendFormat": "",
          "refId": "A"
        }
      ],
      "title": "Latency p95",
      "type": "stat"
    },
    {
      "collapsed": false,
      "gridPos": { "h": 1, "w": 24, "x": 0, "y": 5 },
      "id": 101,
      "panels": [],
      "title": "Request Rate by Service & Endpoint",
      "type": "row"
    },
    {
      "datasource": { "type": "prometheus", "uid": "${datasource}" },
      "fieldConfig": {
        "defaults": {
          "color": { "mode": "palette-classic" },
          "custom": {
            "axisBorderShow": false,
            "axisCenteredZero": false,
            "axisColorMode": "text",
            "axisLabel": "",
            "axisPlacement": "auto",
            "barAlignment": 0,
            "drawStyle": "line",
            "fillOpacity": 10,
            "gradientMode": "none",
            "hideFrom": { "legend": false, "tooltip": false, "viz": false },
            "insertNulls": false,
            "lineInterpolation": "smooth",
            "lineWidth": 1,
            "pointSize": 5,
            "scaleDistribution": { "type": "linear" },
            "showPoints": "never",
            "spanNulls": false,
            "stacking": { "group": "A", "mode": "none" },
            "thresholdsStyle": { "mode": "off" }
          },
          "mappings": [],
          "thresholds": { "mode": "absolute", "steps": [{ "color": "green", "value": null }] },
          "unit": "reqps"
        },
        "overrides": []
      },
      "gridPos": { "h": 8, "w": 12, "x": 0, "y": 6 },
      "id": 10,
      "options": {
        "legend": { "calcs": ["mean", "max"], "displayMode": "table", "placement": "right", "showLegend": true },
        "tooltip": { "mode": "multi", "sort": "desc" }
      },
      "pluginVersion": "10.2.0",
      "targets": [
        {
          "datasource": { "type": "prometheus", "uid": "${datasource}" },
          "expr": "sum(rate(board_service_http_requests_total{namespace=~\"$namespace\"}[5m])) by (endpoint)",
          "legendFormat": "board: {{endpoint}}",
          "refId": "A"
        },
        {
          "datasource": { "type": "prometheus", "uid": "${datasource}" },
          "expr": "sum(rate(user_service_http_requests_total{namespace=~\"$namespace\"}[5m])) by (endpoint)",
          "legendFormat": "user: {{endpoint}}",
          "refId": "B"
        },
        {
          "datasource": { "type": "prometheus", "uid": "${datasource}" },
          "expr": "sum(rate(chat_service_http_requests_total{namespace=~\"$namespace\"}[5m])) by (endpoint)",
          "legendFormat": "chat: {{endpoint}}",
          "refId": "C"
        },
        {
          "datasource": { "type": "prometheus", "uid": "${datasource}" },
          "expr": "sum(rate(noti_service_http_requests_total{namespace=~\"$namespace\"}[5m])) by (endpoint)",
          "legendFormat": "noti: {{endpoint}}",
          "refId": "D"
        },
        {
          "datasource": { "type": "prometheus", "uid": "${datasource}" },
          "expr": "sum(rate(storage_service_http_requests_total{namespace=~\"$namespace\"}[5m])) by (endpoint)",
          "legendFormat": "storage: {{endpoint}}",
          "refId": "E"
        },
        {
          "datasource": { "type": "prometheus", "uid": "${datasource}" },
          "expr": "sum(rate(http_server_requests_seconds_count{namespace=~\"$namespace\"}[5m])) by (uri)",
          "legendFormat": "auth: {{uri}}",
          "refId": "F"
        }
      ],
      "title": "RPS by Service & Endpoint",
      "type": "timeseries"
    },
    {
      "datasource": { "type": "prometheus", "uid": "${datasource}" },
      "fieldConfig": {
        "defaults": {
          "color": { "mode": "palette-classic" },
          "custom": {
            "axisBorderShow": false,
            "axisCenteredZero": false,
            "axisColorMode": "text",
            "axisLabel": "",
            "axisPlacement": "auto",
            "barAlignment": 0,
            "drawStyle": "line",
            "fillOpacity": 10,
            "gradientMode": "none",
            "hideFrom": { "legend": false, "tooltip": false, "viz": false },
            "insertNulls": false,
            "lineInterpolation": "smooth",
            "lineWidth": 1,
            "pointSize": 5,
            "scaleDistribution": { "type": "linear" },
            "showPoints": "never",
            "spanNulls": false,
            "stacking": { "group": "A", "mode": "none" },
            "thresholdsStyle": { "mode": "off" }
          },
          "mappings": [],
          "thresholds": { "mode": "absolute", "steps": [{ "color": "green", "value": null }] },
          "unit": "reqps"
        },
        "overrides": []
      },
      "gridPos": { "h": 8, "w": 12, "x": 12, "y": 6 },
      "id": 11,
      "options": {
        "legend": { "calcs": ["mean", "max"], "displayMode": "table", "placement": "right", "showLegend": true },
        "tooltip": { "mode": "multi", "sort": "desc" }
      },
      "pluginVersion": "10.2.0",
      "targets": [
        {
          "datasource": { "type": "prometheus", "uid": "${datasource}" },
          "expr": "sum(rate({__name__=~\".*_service_http_requests_total\", namespace=~\"$namespace\"}[5m])) by (method)",
          "legendFormat": "{{method}}",
          "refId": "A"
        }
      ],
      "title": "RPS by HTTP Method",
      "type": "timeseries"
    },
    {
      "collapsed": false,
      "gridPos": { "h": 1, "w": 24, "x": 0, "y": 14 },
      "id": 102,
      "panels": [],
      "title": "Latency by Service",
      "type": "row"
    },
    {
      "datasource": { "type": "prometheus", "uid": "${datasource}" },
      "fieldConfig": {
        "defaults": {
          "color": { "mode": "palette-classic" },
          "custom": {
            "axisBorderShow": false,
            "axisCenteredZero": false,
            "axisColorMode": "text",
            "axisLabel": "",
            "axisPlacement": "auto",
            "barAlignment": 0,
            "drawStyle": "line",
            "fillOpacity": 10,
            "gradientMode": "none",
            "hideFrom": { "legend": false, "tooltip": false, "viz": false },
            "insertNulls": false,
            "lineInterpolation": "smooth",
            "lineWidth": 1,
            "pointSize": 5,
            "scaleDistribution": { "type": "linear" },
            "showPoints": "never",
            "spanNulls": false,
            "stacking": { "group": "A", "mode": "none" },
            "thresholdsStyle": { "mode": "line" }
          },
          "mappings": [],
          "thresholds": {
            "mode": "absolute",
            "steps": [
              { "color": "green", "value": null },
              { "color": "yellow", "value": 300 },
              { "color": "red", "value": 500 }
            ]
          },
          "unit": "ms"
        },
        "overrides": []
      },
      "gridPos": { "h": 8, "w": 12, "x": 0, "y": 15 },
      "id": 20,
      "options": {
        "legend": { "calcs": ["mean", "max"], "displayMode": "table", "placement": "right", "showLegend": true },
        "tooltip": { "mode": "multi", "sort": "desc" }
      },
      "pluginVersion": "10.2.0",
      "targets": [
        {
          "datasource": { "type": "prometheus", "uid": "${datasource}" },
          "expr": "histogram_quantile(0.95, sum(rate(board_service_http_request_duration_seconds_bucket{namespace=~\"$namespace\"}[5m])) by (le)) * 1000",
          "legendFormat": "board-service p95",
          "refId": "A"
        },
        {
          "datasource": { "type": "prometheus", "uid": "${datasource}" },
          "expr": "histogram_quantile(0.95, sum(rate(user_service_http_request_duration_seconds_bucket{namespace=~\"$namespace\"}[5m])) by (le)) * 1000",
          "legendFormat": "user-service p95",
          "refId": "B"
        },
        {
          "datasource": { "type": "prometheus", "uid": "${datasource}" },
          "expr": "histogram_quantile(0.95, sum(rate(chat_service_http_request_duration_seconds_bucket{namespace=~\"$namespace\"}[5m])) by (le)) * 1000",
          "legendFormat": "chat-service p95",
          "refId": "C"
        },
        {
          "datasource": { "type": "prometheus", "uid": "${datasource}" },
          "expr": "histogram_quantile(0.95, sum(rate(noti_service_http_request_duration_seconds_bucket{namespace=~\"$namespace\"}[5m])) by (le)) * 1000",
          "legendFormat": "noti-service p95",
          "refId": "D"
        },
        {
          "datasource": { "type": "prometheus", "uid": "${datasource}" },
          "expr": "histogram_quantile(0.95, sum(rate(storage_service_http_request_duration_seconds_bucket{namespace=~\"$namespace\"}[5m])) by (le)) * 1000",
          "legendFormat": "storage-service p95",
          "refId": "E"
        }
      ],
      "title": "Latency p95 by Service",
      "type": "timeseries"
    },
    {
      "datasource": { "type": "prometheus", "uid": "${datasource}" },
      "fieldConfig": {
        "defaults": {
          "color": { "mode": "palette-classic" },
          "custom": {
            "axisBorderShow": false,
            "axisCenteredZero": false,
            "axisColorMode": "text",
            "axisLabel": "",
            "axisPlacement": "auto",
            "barAlignment": 0,
            "drawStyle": "line",
            "fillOpacity": 10,
            "gradientMode": "none",
            "hideFrom": { "legend": false, "tooltip": false, "viz": false },
            "insertNulls": false,
            "lineInterpolation": "smooth",
            "lineWidth": 1,
            "pointSize": 5,
            "scaleDistribution": { "type": "linear" },
            "showPoints": "never",
            "spanNulls": false,
            "stacking": { "group": "A", "mode": "none" },
            "thresholdsStyle": { "mode": "line" }
          },
          "mappings": [],
          "thresholds": {
            "mode": "absolute",
            "steps": [
              { "color": "green", "value": null },
              { "color": "yellow", "value": 500 },
              { "color": "red", "value": 1000 }
            ]
          },
          "unit": "ms"
        },
        "overrides": []
      },
      "gridPos": { "h": 8, "w": 12, "x": 12, "y": 15 },
      "id": 21,
      "options": {
        "legend": { "calcs": ["mean", "max"], "displayMode": "table", "placement": "right", "showLegend": true },
        "tooltip": { "mode": "multi", "sort": "desc" }
      },
      "pluginVersion": "10.2.0",
      "targets": [
        {
          "datasource": { "type": "prometheus", "uid": "${datasource}" },
          "expr": "histogram_quantile(0.99, sum(rate(board_service_http_request_duration_seconds_bucket{namespace=~\"$namespace\"}[5m])) by (le)) * 1000",
          "legendFormat": "board-service p99",
          "refId": "A"
        },
        {
          "datasource": { "type": "prometheus", "uid": "${datasource}" },
          "expr": "histogram_quantile(0.99, sum(rate(user_service_http_request_duration_seconds_bucket{namespace=~\"$namespace\"}[5m])) by (le)) * 1000",
          "legendFormat": "user-service p99",
          "refId": "B"
        },
        {
          "datasource": { "type": "prometheus", "uid": "${datasource}" },
          "expr": "histogram_quantile(0.99, sum(rate(chat_service_http_request_duration_seconds_bucket{namespace=~\"$namespace\"}[5m])) by (le)) * 1000",
          "legendFormat": "chat-service p99",
          "refId": "C"
        },
        {
          "datasource": { "type": "prometheus", "uid": "${datasource}" },
          "expr": "histogram_quantile(0.99, sum(rate(noti_service_http_request_duration_seconds_bucket{namespace=~\"$namespace\"}[5m])) by (le)) * 1000",
          "legendFormat": "noti-service p99",
          "refId": "D"
        },
        {
          "datasource": { "type": "prometheus", "uid": "${datasource}" },
          "expr": "histogram_quantile(0.99, sum(rate(storage_service_http_request_duration_seconds_bucket{namespace=~\"$namespace\"}[5m])) by (le)) * 1000",
          "legendFormat": "storage-service p99",
          "refId": "E"
        }
      ],
      "title": "Latency p99 by Service",
      "type": "timeseries"
    },
    {
      "collapsed": false,
      "gridPos": { "h": 1, "w": 24, "x": 0, "y": 23 },
      "id": 103,
      "panels": [],
      "title": "Top Endpoints",
      "type": "row"
    },
    {
      "datasource": { "type": "prometheus", "uid": "${datasource}" },
      "description": "Top 10 slowest endpoints by p95 latency",
      "fieldConfig": {
        "defaults": {
          "color": { "mode": "thresholds" },
          "custom": {
            "align": "auto",
            "cellOptions": { "type": "auto" },
            "inspect": false
          },
          "mappings": [],
          "thresholds": {
            "mode": "absolute",
            "steps": [
              { "color": "green", "value": null },
              { "color": "yellow", "value": 300 },
              { "color": "red", "value": 500 }
            ]
          },
          "unit": "ms"
        },
        "overrides": [
          {
            "matcher": { "id": "byName", "options": "service" },
            "properties": [{ "id": "custom.width", "value": 120 }]
          },
          {
            "matcher": { "id": "byName", "options": "endpoint" },
            "properties": [{ "id": "custom.width", "value": 250 }]
          },
          {
            "matcher": { "id": "byName", "options": "Value" },
            "properties": [
              { "id": "custom.cellOptions", "value": { "mode": "gradient", "type": "gauge" } },
              { "id": "min", "value": 0 },
              { "id": "max", "value": 1000 },
              { "id": "displayName", "value": "p95 Latency" }
            ]
          }
        ]
      },
      "gridPos": { "h": 10, "w": 12, "x": 0, "y": 24 },
      "id": 30,
      "options": {
        "cellHeight": "sm",
        "footer": { "countRows": false, "enablePagination": false, "fields": "", "reducer": ["sum"], "show": false },
        "showHeader": true,
        "sortBy": [{ "desc": true, "displayName": "Value" }]
      },
      "pluginVersion": "10.2.0",
      "targets": [
        {
          "datasource": { "type": "prometheus", "uid": "${datasource}" },
          "expr": "topk(10, histogram_quantile(0.95, sum(rate(board_service_http_request_duration_seconds_bucket{namespace=~\"$namespace\"}[5m])) by (endpoint, le)) * 1000)",
          "format": "table",
          "instant": true,
          "legendFormat": "",
          "refId": "A"
        },
        {
          "datasource": { "type": "prometheus", "uid": "${datasource}" },
          "expr": "topk(10, histogram_quantile(0.95, sum(rate(user_service_http_request_duration_seconds_bucket{namespace=~\"$namespace\"}[5m])) by (endpoint, le)) * 1000)",
          "format": "table",
          "instant": true,
          "legendFormat": "",
          "refId": "B"
        },
        {
          "datasource": { "type": "prometheus", "uid": "${datasource}" },
          "expr": "topk(10, histogram_quantile(0.95, sum(rate(chat_service_http_request_duration_seconds_bucket{namespace=~\"$namespace\"}[5m])) by (endpoint, le)) * 1000)",
          "format": "table",
          "instant": true,
          "legendFormat": "",
          "refId": "C"
        }
      ],
      "title": "Slowest Endpoints (p95)",
      "transformations": [
        {
          "id": "merge",
          "options": {}
        },
        {
          "id": "organize",
          "options": {
            "excludeByName": { "Time": true },
            "indexByName": {},
            "renameByName": {}
          }
        }
      ],
      "type": "table"
    },
    {
      "datasource": { "type": "prometheus", "uid": "${datasource}" },
      "description": "Top 10 endpoints by request count",
      "fieldConfig": {
        "defaults": {
          "color": { "mode": "palette-classic" },
          "custom": {
            "align": "auto",
            "cellOptions": { "type": "auto" },
            "inspect": false
          },
          "mappings": [],
          "thresholds": { "mode": "absolute", "steps": [{ "color": "green", "value": null }] },
          "unit": "reqps"
        },
        "overrides": [
          {
            "matcher": { "id": "byName", "options": "endpoint" },
            "properties": [{ "id": "custom.width", "value": 250 }]
          },
          {
            "matcher": { "id": "byName", "options": "Value" },
            "properties": [
              { "id": "custom.cellOptions", "value": { "mode": "gradient", "type": "gauge" } },
              { "id": "min", "value": 0 },
              { "id": "displayName", "value": "RPS" }
            ]
          }
        ]
      },
      "gridPos": { "h": 10, "w": 12, "x": 12, "y": 24 },
      "id": 31,
      "options": {
        "cellHeight": "sm",
        "footer": { "countRows": false, "enablePagination": false, "fields": "", "reducer": ["sum"], "show": false },
        "showHeader": true,
        "sortBy": [{ "desc": true, "displayName": "Value" }]
      },
      "pluginVersion": "10.2.0",
      "targets": [
        {
          "datasource": { "type": "prometheus", "uid": "${datasource}" },
          "expr": "topk(5, sum(rate(board_service_http_requests_total{namespace=~\"$namespace\"}[5m])) by (endpoint))",
          "format": "table",
          "instant": true,
          "legendFormat": "",
          "refId": "A"
        },
        {
          "datasource": { "type": "prometheus", "uid": "${datasource}" },
          "expr": "topk(5, sum(rate(user_service_http_requests_total{namespace=~\"$namespace\"}[5m])) by (endpoint))",
          "format": "table",
          "instant": true,
          "legendFormat": "",
          "refId": "B"
        },
        {
          "datasource": { "type": "prometheus", "uid": "${datasource}" },
          "expr": "topk(5, sum(rate(chat_service_http_requests_total{namespace=~\"$namespace\"}[5m])) by (endpoint))",
          "format": "table",
          "instant": true,
          "legendFormat": "",
          "refId": "C"
        }
      ],
      "title": "Busiest Endpoints (RPS)",
      "transformations": [
        {
          "id": "merge",
          "options": {}
        },
        {
          "id": "organize",
          "options": {
            "excludeByName": { "Time": true },
            "indexByName": {},
            "renameByName": {}
          }
        }
      ],
      "type": "table"
    },
    {
      "collapsed": false,
      "gridPos": { "h": 1, "w": 24, "x": 0, "y": 34 },
      "id": 104,
      "panels": [],
      "title": "Error Analysis",
      "type": "row"
    },
    {
      "datasource": { "type": "prometheus", "uid": "${datasource}" },
      "fieldConfig": {
        "defaults": {
          "color": { "mode": "palette-classic" },
          "custom": {
            "axisBorderShow": false,
            "axisCenteredZero": false,
            "axisColorMode": "text",
            "axisLabel": "",
            "axisPlacement": "auto",
            "barAlignment": 0,
            "drawStyle": "line",
            "fillOpacity": 10,
            "gradientMode": "none",
            "hideFrom": { "legend": false, "tooltip": false, "viz": false },
            "insertNulls": false,
            "lineInterpolation": "smooth",
            "lineWidth": 1,
            "pointSize": 5,
            "scaleDistribution": { "type": "linear" },
            "showPoints": "never",
            "spanNulls": false,
            "stacking": { "group": "A", "mode": "none" },
            "thresholdsStyle": { "mode": "line+area" }
          },
          "mappings": [],
          "max": 100,
          "min": 0,
          "thresholds": {
            "mode": "absolute",
            "steps": [
              { "color": "green", "value": null },
              { "color": "yellow", "value": 1 },
              { "color": "red", "value": 5 }
            ]
          },
          "unit": "percent"
        },
        "overrides": []
      },
      "gridPos": { "h": 8, "w": 12, "x": 0, "y": 35 },
      "id": 40,
      "options": {
        "legend": { "calcs": ["mean", "max"], "displayMode": "table", "placement": "right", "showLegend": true },
        "tooltip": { "mode": "multi", "sort": "desc" }
      },
      "pluginVersion": "10.2.0",
      "targets": [
        {
          "datasource": { "type": "prometheus", "uid": "${datasource}" },
          "expr": "100 * sum(rate(board_service_http_requests_total{namespace=~\"$namespace\", status=\"5xx\"}[5m])) / sum(rate(board_service_http_requests_total{namespace=~\"$namespace\"}[5m]))",
          "legendFormat": "board-service",
          "refId": "A"
        },
        {
          "datasource": { "type": "prometheus", "uid": "${datasource}" },
          "expr": "100 * sum(rate(user_service_http_requests_total{namespace=~\"$namespace\", status=\"5xx\"}[5m])) / sum(rate(user_service_http_requests_total{namespace=~\"$namespace\"}[5m]))",
          "legendFormat": "user-service",
          "refId": "B"
        },
        {
          "datasource": { "type": "prometheus", "uid": "${datasource}" },
          "expr": "100 * sum(rate(chat_service_http_requests_total{namespace=~\"$namespace\", status=\"5xx\"}[5m])) / sum(rate(chat_service_http_requests_total{namespace=~\"$namespace\"}[5m]))",
          "legendFormat": "chat-service",
          "refId": "C"
        },
        {
          "datasource": { "type": "prometheus", "uid": "${datasource}" },
          "expr": "100 * sum(rate(noti_service_http_requests_total{namespace=~\"$namespace\", status=\"5xx\"}[5m])) / sum(rate(noti_service_http_requests_total{namespace=~\"$namespace\"}[5m]))",
          "legendFormat": "noti-service",
          "refId": "D"
        },
        {
          "datasource": { "type": "prometheus", "uid": "${datasource}" },
          "expr": "100 * sum(rate(storage_service_http_requests_total{namespace=~\"$namespace\", status=\"5xx\"}[5m])) / sum(rate(storage_service_http_requests_total{namespace=~\"$namespace\"}[5m]))",
          "legendFormat": "storage-service",
          "refId": "E"
        },
        {
          "datasource": { "type": "prometheus", "uid": "${datasource}" },
          "expr": "100 * sum(rate(http_server_requests_seconds_count{namespace=~\"$namespace\", status=~\"5.*\"}[5m])) / sum(rate(http_server_requests_seconds_count{namespace=~\"$namespace\"}[5m]))",
          "legendFormat": "auth-service",
          "refId": "F"
        }
      ],
      "title": "5xx Error Rate by Service",
      "type": "timeseries"
    },
    {
      "datasource": { "type": "prometheus", "uid": "${datasource}" },
      "fieldConfig": {
        "defaults": {
          "color": { "mode": "palette-classic" },
          "custom": {
            "axisBorderShow": false,
            "axisCenteredZero": false,
            "axisColorMode": "text",
            "axisLabel": "",
            "axisPlacement": "auto",
            "barAlignment": 0,
            "drawStyle": "bars",
            "fillOpacity": 50,
            "gradientMode": "none",
            "hideFrom": { "legend": false, "tooltip": false, "viz": false },
            "insertNulls": false,
            "lineInterpolation": "linear",
            "lineWidth": 1,
            "pointSize": 5,
            "scaleDistribution": { "type": "linear" },
            "showPoints": "never",
            "spanNulls": false,
            "stacking": { "group": "A", "mode": "normal" },
            "thresholdsStyle": { "mode": "off" }
          },
          "mappings": [],
          "thresholds": { "mode": "absolute", "steps": [{ "color": "green", "value": null }] },
          "unit": "short"
        },
        "overrides": [
          { "matcher": { "id": "byRegexp", "options": "2xx" }, "properties": [{ "id": "color", "value": { "fixedColor": "green", "mode": "fixed" } }] },
          { "matcher": { "id": "byRegexp", "options": "4xx" }, "properties": [{ "id": "color", "value": { "fixedColor": "yellow", "mode": "fixed" } }] },
          { "matcher": { "id": "byRegexp", "options": "5xx" }, "properties": [{ "id": "color", "value": { "fixedColor": "red", "mode": "fixed" } }] }
        ]
      },
      "gridPos": { "h": 8, "w": 12, "x": 12, "y": 35 },
      "id": 41,
      "options": {
        "legend": { "calcs": ["sum"], "displayMode": "table", "placement": "right", "showLegend": true },
        "tooltip": { "mode": "multi", "sort": "desc" }
      },
      "pluginVersion": "10.2.0",
      "targets": [
        {
          "datasource": { "type": "prometheus", "uid": "${datasource}" },
          "expr": "sum(increase({__name__=~\".*_service_http_requests_total\", namespace=~\"$namespace\"}[5m])) by (status)",
          "legendFormat": "{{status}}",
          "refId": "A"
        }
      ],
      "title": "Requests by Status Category",
      "type": "timeseries"
    }
  ],
  "refresh": "30s",
  "schemaVersion": 38,
  "tags": ["wealist", "api", "performance", "v2"],
  "templating": {
    "list": [
      {
        "current": { "selected": false, "text": "prometheus", "value": "prometheus" },
        "hide": 0,
        "includeAll": false,
        "label": "Datasource",
        "multi": false,
        "name": "datasource",
        "options": [],
        "query": "prometheus",
        "refresh": 1,
        "regex": "",
        "skipUrlSync": false,
        "type": "datasource"
      },
      {
        "current": {},
        "datasource": { "type": "prometheus", "uid": "${datasource}" },
        "definition": "label_values(kube_pod_info, namespace)",
        "hide": 0,
        "includeAll": true,
        "label": "Namespace",
        "multi": false,
        "name": "namespace",
        "options": [],
        "query": { "query": "label_values(kube_pod_info, namespace)", "refId": "StandardVariableQuery" },
        "refresh": 2,
        "regex": "wealist.*",
        "skipUrlSync": false,
        "sort": 1,
        "type": "query"
      }
    ]
  },
  "time": { "from": "now-1h", "to": "now" },
  "timepicker": {},
  "timezone": "browser",
  "title": "API Performance (v2)",
  "uid": "api-performance-v2",
  "version": 1,
  "weekStart": ""
}
